pypfopt/__init__.py
pypfopt/base_optimizer.py
pypfopt/black_litterman.py
pypfopt/cla.py
pypfopt/discrete_allocation.py
pypfopt/efficient_frontier/__init__.py
pypfopt/efficient_frontier/efficient_cdar.py
pypfopt/efficient_frontier/efficient_cvar.py
pypfopt/efficient_frontier/efficient_frontier.py
pypfopt/efficient_frontier/efficient_semivariance.py
pypfopt/exceptions.py
pypfopt/expected_returns.py
pypfopt/hierarchical_portfolio.py
pypfopt/objective_functions.py
pypfopt/plotting.py
pypfopt/risk_models.py
pyportfolioopt-1.5.0.dist-info/LICENSE.txt
pyportfolioopt-1.5.0.dist-info/WHEEL
pyportfolioopt-1.5.0.dist-info/METADATA
pyportfolioopt-1.5.0.dist-info/RECORD
