Metadata-Version: 2.1
Name: pyportfolioopt
Version: 1.5.0
Summary: Financial portfolio optimization in python
Home-page: https://github.com/robertmartin8/PyPortfolioOpt
License: MIT
Keywords: finance,portfolio,optimization,quant,investing
Author: Robert Andrew Martin
Author-email: martin.robertandrew@gmail.com
Requires-Python: >=3.6.1,<4.0.0
Classifier: Development Status :: 4 - Beta
Classifier: Environment :: Console
Classifier: Intended Audience :: Financial and Insurance Industry
Classifier: Intended Audience :: Science/Research
Classifier: License :: OSI Approved :: MIT License
Classifier: Natural Language :: English
Classifier: Operating System :: OS Independent
Classifier: Programming Language :: Python :: 3
Classifier: Programming Language :: Python :: 3 :: Only
Classifier: Programming Language :: Python :: 3.6
Classifier: Programming Language :: Python :: 3.7
Classifier: Programming Language :: Python :: 3.8
Classifier: Programming Language :: Python :: 3.9
Classifier: Topic :: Office/Business :: Financial
Classifier: Topic :: Office/Business :: Financial :: Investment
Classifier: Topic :: Scientific/Engineering :: Mathematics
Provides-Extra: optionals
Requires-Dist: cvxopt (>=1.2,<2.0,!=1.2.5.post1); extra == "optionals"
Requires-Dist: cvxpy (>=1.1.10,<2.0.0)
Requires-Dist: matplotlib (>=3.2.0,<4.0.0); extra == "optionals"
Requires-Dist: numpy (>=1.12,<2.0)
Requires-Dist: pandas (>=0.19)
Requires-Dist: scikit-learn (>=0.24.1,<0.25.0); extra == "optionals"
Requires-Dist: scipy (>=1.3,<2.0)
Project-URL: Documentation, https://pyportfolioopt.readthedocs.io/en/latest/
Project-URL: Issues, https://github.com/robertmartin8/PyPortfolioOpt/issues
Project-URL: Personal website, https://reasonabledeviations.com
Project-URL: Repository, https://github.com/robertmartin8/PyPortfolioOpt
